tideway/__init__.py
tideway/admin.py
tideway/credentials.py
tideway/data.py
tideway/discoRequests.py
tideway/discovery.py
tideway/endpoints.py
tideway/events.py
tideway/kerberos.py
tideway/knowledge.py
tideway/main.py
tideway/models.py
tideway/security.py
tideway/taxonomy.py
tideway/topology.py
tideway/vault.py
tideway-0.2.1.dist-info/licenses/LICENSE
tideway-0.2.1.dist-info/METADATA
tideway-0.2.1.dist-info/WHEEL
tideway-0.2.1.dist-info/top_level.txt
tideway-0.2.1.dist-info/RECORD
