Metadata-Version: 2.4
Name: tideway
Version: 0.2.1
Summary: Library for BMC Discovery API Interface.
Home-page: https://github.com/traversys/Tideway
Author: Wes Moskal-Fitzpatrick
Author-email: wes@traversys.io
Classifier: Programming Language :: Python :: 3
Classifier: License :: OSI Approved :: MIT License
Classifier: Operating System :: OS Independent
Requires-Python: >=3.7
License-File: LICENSE
Requires-Dist: requests
Dynamic: author
Dynamic: author-email
Dynamic: classifier
Dynamic: description
Dynamic: description-content-type
Dynamic: home-page
Dynamic: license-file
Dynamic: requires-dist
Dynamic: requires-python
Dynamic: summary
